click_web-stubs/METADATA.toml
click_web-stubs/__init__.pyi
click_web-stubs/exceptions.pyi
click_web-stubs/py.typed
click_web-stubs/web_click_types.pyi
click_web-stubs/resources/__init__.pyi
click_web-stubs/resources/cmd_exec.pyi
click_web-stubs/resources/cmd_form.pyi
click_web-stubs/resources/index.pyi
click_web-stubs/resources/input_fields.pyi
types_click_web-0.8.0.20250708.dist-info/licenses/LICENSE
types_click_web-0.8.0.20250708.dist-info/METADATA
types_click_web-0.8.0.20250708.dist-info/WHEEL
types_click_web-0.8.0.20250708.dist-info/top_level.txt
types_click_web-0.8.0.20250708.dist-info/RECORD
